dialograph/__init__.py
dialograph/agent/__init__.py
dialograph/agent/agent.py
dialograph/agent/env.py
dialograph/agent/prompts.py
dialograph/agent/run.py
dialograph/agent/utils.py
dialograph/core/__init__.py
dialograph/core/draw.py
dialograph/core/edge.py
dialograph/core/graph.py
dialograph/core/node.py
dialograph/memory/__init__.py
dialograph/memory/belief.py
dialograph/memory/preference.py
dialograph/memory/strategy.py
dialograph/traversal/__init__.py
dialograph/traversal/retrieve.py
dialograph/traversal/score.py
dialograph/utils/__init__.py
dialograph/utils/export.py
dialograph/utils/io.py
dialograph-0.7.0.dist-info/METADATA
dialograph-0.7.0.dist-info/WHEEL
dialograph-0.7.0.dist-info/top_level.txt
dialograph-0.7.0.dist-info/RECORD
