Metadata-Version: 2.4
Name: dialograph
Version: 0.7.0
Summary: Dialograph is a Python toolkit for building, evolving, and reasoning over temporal dialogue graphs for proactive conversational agents.
Author: author
Requires-Python: >=3.11
Requires-Dist: graphviz>=0.21
Requires-Dist: networkx>=3.6.1
Requires-Dist: numpy>=2.4.0
Requires-Dist: pydantic>=2.12.5
Requires-Dist: pydantic-ai>=1.44.0
Requires-Dist: pyvis>=0.3.2
